tf_serving_client/__init__.py
tf_serving_client/predict_client/__init__.py
tf_serving_client/predict_client/predict_client.py
tf_serving_client/tensorflow_serving/__init__.py
tf_serving_client/tensorflow_serving/apis/__init__.py
tf_serving_client/tensorflow_serving/apis/classification_pb2.py
tf_serving_client/tensorflow_serving/apis/get_model_metadata_pb2.py
tf_serving_client/tensorflow_serving/apis/inference_pb2.py
tf_serving_client/tensorflow_serving/apis/input_pb2.py
tf_serving_client/tensorflow_serving/apis/model_pb2.py
tf_serving_client/tensorflow_serving/apis/model_service_pb2.py
tf_serving_client/tensorflow_serving/apis/model_service_pb2_grpc.py
tf_serving_client/tensorflow_serving/apis/predict_pb2.py
tf_serving_client/tensorflow_serving/apis/prediction_service_pb2.py
tf_serving_client/tensorflow_serving/apis/regression_pb2.py
tf_serving_client-0.1.9.dist-info/DESCRIPTION.rst
tf_serving_client-0.1.9.dist-info/METADATA
tf_serving_client-0.1.9.dist-info/RECORD
tf_serving_client-0.1.9.dist-info/WHEEL
tf_serving_client-0.1.9.dist-info/metadata.json
tf_serving_client-0.1.9.dist-info/top_level.txt
tf_serving_client-0.1.9.dist-info/zip-safe
