Metadata-Version: 2.0
Name: tf-serving-client
Version: 0.1.9
Summary: Customised Tensorflow Serving API produced by coffeedjimmy
Home-page: https://github.com/coffeedjimmy/tf_serving_client.git
Author: Jimmy Woo
Author-email: coffeedjimmy@gmail.com
License: Apache 2.0
Keywords: TensorFlow Serving API libraries
Platform: UNKNOWN
Classifier: Development Status :: 3 - Alpha
Classifier: Intended Audience :: Developers
Classifier: Natural Language :: English
Classifier: Programming Language :: Python :: 3.5
Classifier: Programming Language :: Python :: 3.6
Classifier: Programming Language :: Python :: 3 :: Only
Classifier: Operating System :: OS Independent
Requires-Python: ~=3.5
Requires-Dist: grpcio (>=1.7.0)
Requires-Dist: numpy (>=1.12.0)
